stix_shifter_modules/reaqta/__init__.py
stix_shifter_modules/reaqta/entry_point.py
stix_shifter_modules/reaqta/configuration/config.json
stix_shifter_modules/reaqta/configuration/dialects.json
stix_shifter_modules/reaqta/configuration/lang_en.json
stix_shifter_modules/reaqta/stix_translation/__init__.py
stix_shifter_modules/reaqta/stix_translation/json_to_stix_translator.py
stix_shifter_modules/reaqta/stix_translation/query_constructor.py
stix_shifter_modules/reaqta/stix_translation/query_translator.py
stix_shifter_modules/reaqta/stix_translation/transformers.py
stix_shifter_modules/reaqta/stix_translation/json/event_names_map.json
stix_shifter_modules/reaqta/stix_translation/json/from_stix_map.json
stix_shifter_modules/reaqta/stix_translation/json/network_protocol_map.json
stix_shifter_modules/reaqta/stix_translation/json/operators.json
stix_shifter_modules/reaqta/stix_translation/json/to_stix_map.json
stix_shifter_modules/reaqta/stix_translation/json/stix_2_1/from_stix_map.json
stix_shifter_modules/reaqta/stix_translation/json/stix_2_1/to_stix_map.json
stix_shifter_modules/reaqta/stix_transmission/__init__.py
stix_shifter_modules/reaqta/stix_transmission/api_client.py
stix_shifter_modules/reaqta/stix_transmission/connector.py
stix_shifter_modules/reaqta/test/stix_translation/json/event_result.json
stix_shifter_modules_reaqta-8.0.2.dist-info/licenses/AUTHORS.md
stix_shifter_modules_reaqta-8.0.2.dist-info/licenses/LICENSE.md
stix_shifter_modules_reaqta-8.0.2.dist-info/licenses/NOTICE
stix_shifter_modules_reaqta-8.0.2.dist-info/METADATA
stix_shifter_modules_reaqta-8.0.2.dist-info/WHEEL
stix_shifter_modules_reaqta-8.0.2.dist-info/top_level.txt
stix_shifter_modules_reaqta-8.0.2.dist-info/RECORD
